roebuck/__init__.py
roebuck/roebuck.py
roebuck-0.0.6.dist-info/LICENSE
roebuck-0.0.6.dist-info/METADATA
roebuck-0.0.6.dist-info/WHEEL
roebuck-0.0.6.dist-info/top_level.txt
roebuck-0.0.6.dist-info/RECORD
