Metadata-Version: 2.1
Name: roebuck
Version: 0.0.6
Summary: Renders the legend who is Roebuck
Home-page: UNKNOWN
Author: Peter Cooper
Author-email: peter@peterc.org
License: UNKNOWN
Platform: UNKNOWN
